MANIFEST.in
pavement.py
paver-minilib.zip
setup.cfg
setup.py
pydap/__init__.py
pydap.wsgi.ssf.egg-info/PKG-INFO
pydap.wsgi.ssf.egg-info/SOURCES.txt
pydap.wsgi.ssf.egg-info/dependency_links.txt
pydap.wsgi.ssf.egg-info/entry_points.txt
pydap.wsgi.ssf.egg-info/namespace_packages.txt
pydap.wsgi.ssf.egg-info/not-zip-safe
pydap.wsgi.ssf.egg-info/requires.txt
pydap.wsgi.ssf.egg-info/top_level.txt
pydap/wsgi/__init__.py
pydap/wsgi/ssf/__init__.py
pydap/wsgi/ssf/functions.py