Metadata-Version: 1.1
Name: pydap.wsgi.ssf
Version: 0.1.1.1
Summary: WSGI middleware implementing Opendap server-side functions on the Pydap server.
Home-page: http://pydap.org/
Author: Roberto De Almeida
Author-email: rob@pydap.org
License: MIT
Keywords: opendap dods dap data science climate oceanography meteorology
Platform: UNKNOWN
Classifier: Development Status :: 5 - Production/Stable
Classifier: Environment :: Console
Classifier: Environment :: Web Environment
Classifier: Framework :: Paste
Classifier: Intended Audience :: Developers
Classifier: Intended Audience :: Science/Research
Classifier: License :: OSI Approved :: MIT License
Classifier: Operating System :: OS Independent
Classifier: Programming Language :: Python
Classifier: Topic :: Internet
Classifier: Topic :: Internet :: WWW/HTTP :: WSGI
Classifier: Topic :: Scientific/Engineering
Classifier: Topic :: Software Development :: Libraries :: Python Modules
